tree_sitter_llvm/__init__.py
tree_sitter_llvm/__init__.pyi
tree_sitter_llvm/_binding.abi3.so
tree_sitter_llvm/binding.c
tree_sitter_llvm/py.typed
tree_sitter_llvm/queries/highlights.scm
tree_sitter_llvm-1.1.0.dist-info/METADATA
tree_sitter_llvm-1.1.0.dist-info/WHEEL
tree_sitter_llvm-1.1.0.dist-info/top_level.txt
tree_sitter_llvm-1.1.0.dist-info/RECORD
tree_sitter_llvm-1.1.0.dist-info/licenses/LICENSE
