Metadata-Version: 2.4
Name: tree-sitter-llvm
Version: 1.1.0
Summary: Llvm grammar for tree-sitter
License: MIT
Project-URL: Homepage, https://github.com/tree-sitter/tree-sitter-llvm
Keywords: incremental,parsing,tree-sitter,llvm
Classifier: Intended Audience :: Developers
Classifier: License :: OSI Approved :: MIT License
Classifier: Topic :: Software Development :: Compilers
Classifier: Topic :: Text Processing :: Linguistic
Classifier: Typing :: Typed
Requires-Python: >=3.10
License-File: LICENSE
Provides-Extra: core
Requires-Dist: tree-sitter~=0.25.6; extra == "core"
Dynamic: license-file
